MANIFEST.in
README.txt
dockerDiscovery.json.example
setup.cfg
setup.py
zabbixAgentd
zabbixDockerDiscovery
ZabbixDockerAgent/__init__.py
ZabbixDockerAgent/dockerdata.py
ZabbixDockerAgent/testRun.py
ZabbixDockerAgent/toolbox.py
ZabbixDockerAgent/zabbix.py
zabbix_docker_agent.egg-info/PKG-INFO
zabbix_docker_agent.egg-info/SOURCES.txt
zabbix_docker_agent.egg-info/dependency_links.txt
zabbix_docker_agent.egg-info/requires.txt
zabbix_docker_agent.egg-info/top_level.txt