Metadata-Version: 1.0
Name: zabbix-docker-agent
Version: 0.2.3
Summary: Zabbix Docker Agent for collecting dynamic container statistics
Home-page: https://github.com/akomic/zabbix-docker-agent
Author: Alen Komic
Author-email: akomic@gmail.com
License: UNKNOWN
Keywords: docker,monitoring,metrics,zabbix
Platform: UNKNOWN
